sphinx_lua/__init__.py
sphinx_lua/directives.py
sphinx_lua/luadoc.py
sphinx_lua/renderers.py
sphinx_lua/version.py
sphinx_lua/templates/attribute.rst
sphinx_lua/templates/class.rst
sphinx_lua/templates/classsummary.rst
sphinx_lua/templates/function.rst
sphinx_lua/templates/method.rst
sphinx_lua/templates/module.rst
sphinx_lua/templates/param_list.rst
sphinx_lua/templates/type.rst
sphinx_lua-1.1.5.dist-info/LICENSE.txt
sphinx_lua-1.1.5.dist-info/METADATA
sphinx_lua-1.1.5.dist-info/WHEEL
sphinx_lua-1.1.5.dist-info/top_level.txt
sphinx_lua-1.1.5.dist-info/RECORD
