Metadata-Version: 2.1
Name: sphinx-lua
Version: 1.1.5
Summary: Support for using Sphinx on Luadoc-documented Lua code
Author: Eliott Dumeix
Author-email: eliott.dumeix@gmail.com
License: MIT
Keywords: sphinx,documentation,docs,lua,luadoc,restructured
Classifier: Intended Audience :: Developers
Classifier: Natural Language :: English
Classifier: License :: OSI Approved :: MIT License
Classifier: Programming Language :: Python :: 3.5
Classifier: Programming Language :: Python :: 3.6
Classifier: Programming Language :: Python :: 3.7
Classifier: Topic :: Documentation :: Sphinx
Classifier: Topic :: Software Development :: Documentation
License-File: LICENSE.txt
Requires-Dist: six
Requires-Dist: Jinja2 (>3.0)
Requires-Dist: luadoc (>=1.3.1)
Requires-Dist: sphinxcontrib-luadomain (>=1.1.1)
